oceanbase_mcp_server/__init__.py
oceanbase_mcp_server/server.py
oceanbase_mcp_server-0.1.0.dist-info/METADATA
oceanbase_mcp_server-0.1.0.dist-info/WHEEL
oceanbase_mcp_server-0.1.0.dist-info/entry_points.txt
oceanbase_mcp_server-0.1.0.dist-info/licenses/LICENSE
oceanbase_mcp_server-0.1.0.dist-info/RECORD
