Metadata-Version: 2.4
Name: oceanbase_mcp_server
Version: 0.1.0
Summary: A Model Context Protocol (MCP) server that enables secure interaction with OceanBase databases. This server allows AI assistants to list tables, read data, and execute SQL queries through a controlled interface, making database exploration and analysis safer and more structured.
Author: yaunoOo
License-File: LICENSE
Requires-Python: >=3.11
Requires-Dist: mcp>=1.0.0
Requires-Dist: mysql-connector-python>=9.1.0
